example_pkg/__init__.py
example_pkg/app.py
python_for_math-1.0.0.dist-info/LICENSE
python_for_math-1.0.0.dist-info/METADATA
python_for_math-1.0.0.dist-info/WHEEL
python_for_math-1.0.0.dist-info/top_level.txt
python_for_math-1.0.0.dist-info/RECORD
