Metadata-Version: 2.1
Name: python-for-math
Version: 1.0.0
Summary: Sort description
Home-page: https://github.com/pypa/sampleproject
Author: TeamPython
Author-email: teampython@gmail.com
Classifier: Programming Language :: Python :: 2
Classifier: License :: OSI Approved :: MIT License
Classifier: Operating System :: OS Independent
License-File: LICENSE
